multitax/__init__.py
multitax/customtx.py
multitax/dummytx.py
multitax/greengenestx.py
multitax/gtdbtx.py
multitax/multitax.py
multitax/ncbitx.py
multitax/otttx.py
multitax/silvatx.py
multitax/utils.py
multitax-1.3.2.dist-info/licenses/LICENSE
multitax-1.3.2.dist-info/METADATA
multitax-1.3.2.dist-info/WHEEL
multitax-1.3.2.dist-info/top_level.txt
multitax-1.3.2.dist-info/RECORD
